{
    "room1": {
        "x": 784.0,
        "y": 22.0
    },
    "room2": {
        "x": 787.0,
        "y": 72.0
    },
    "room3": {
        "x": 791.0,
        "y": 207.0
    },
    "room4": {
        "x": 795.0,
        "y": 348.0
    },
    "room5": {
        "x": 106.0,
        "y": 392.0
    },
    "room6": {
        "x": 738.0,
        "y": 462.0
    },
    "room7": {
        "x": 798.0,
        "y": 448.0
    },
    "room8": {
        "x": 113.0,
        "y": 541.0
    },
    "room9": {
        "x": 621.0,
        "y": 578.0
    },
    "room10": {
        "x": 734.0,
        "y": 553.0
    },
    "room11": {
        "x": 163.0,
        "y": 595.0
    },
    "room12": {
        "x": 224.0,
        "y": 591.0
    },
    "room13": {
        "x": 333.0,
        "y": 588.0
    },
    "room14": {
        "x": 455.0,
        "y": 588.0
    }
}